{
 "_comment": "Flujo de caja libre de los ÚLTIMOS 12 MESES (TTM) por empresa: anual del año pasado − su acumulado al mismo corte + el acumulado de este año. Generado por extractor/fetch_fcf_ttm.py — no editar a mano. Las empresas que no están aquí es porque les faltaba alguna pieza: la app cae sola al trimestre × 4 y lo dice.",
 "generado": "2026-07-23",
 "periodo": {
  "anio": 2026,
  "trimestre": 1
 },
 "fuente": "SMV — EE.FF. individuales (XBRL estructurado)",
 "empresas": {
  "NEXAPEC1": {
   "fcf": 99078000.0,
   "monedaXbrl": "USD",
   "desde": "2025-03-31",
   "hasta": "2026-03-31",
   "piezas": {
    "anualPrevio": 64155000.0,
    "acumuladoPrevio": -70958000.0,
    "acumuladoActual": -36035000.0,
    "anio": 2026,
    "trimestre": 1
   },
   "fuente": {
    "intermedio": "EE.FF. intermedios 2026-T1 (SMV, presentado 06/05/2026)",
    "anual": "EE.FF. anuales 2025 (SMV, presentado 31/03/2026)"
   }
  },
  "BVN": {
   "fcf": 342182000.0,
   "monedaXbrl": "USD",
   "desde": "2025-03-31",
   "hasta": "2026-03-31",
   "piezas": {
    "anualPrevio": 67726000.0,
    "acumuladoPrevio": -71948000.0,
    "acumuladoActual": 202508000.0,
    "anio": 2026,
    "trimestre": 1
   },
   "fuente": {
    "intermedio": "EE.FF. intermedios 2026-T1 (SMV, presentado 29/04/2026)",
    "anual": "EE.FF. anuales 2025 (SMV, presentado 30/03/2026)"
   }
  },
  "CVERDEC1": {
   "fcf": 1692891000.0,
   "monedaXbrl": "USD",
   "desde": "2025-03-31",
   "hasta": "2026-03-31",
   "piezas": {
    "anualPrevio": 1351541000.0,
    "acumuladoPrevio": 167475000.0,
    "acumuladoActual": 508825000.0,
    "anio": 2026,
    "trimestre": 1
   },
   "fuente": {
    "intermedio": "EE.FF. intermedios 2026-T1 (SMV, presentado 24/04/2026)",
    "anual": "EE.FF. anuales 2025 (SMV, presentado 23/03/2026)"
   }
  },
  "ALICORC1": {
   "fcf": 672068000.0,
   "monedaXbrl": "USD",
   "desde": "2025-03-31",
   "hasta": "2026-03-31",
   "piezas": {
    "anualPrevio": 414599000.0,
    "acumuladoPrevio": 176211000.0,
    "acumuladoActual": 433680000.0,
    "anio": 2026,
    "trimestre": 1
   },
   "fuente": {
    "intermedio": "EE.FF. intermedios 2026-T1 (SMV, presentado 29/04/2026)",
    "anual": "EE.FF. anuales 2025 (SMV, presentado 31/03/2026)"
   }
  },
  "GLORIAI1": {
   "fcf": 279901000.0,
   "monedaXbrl": "PEN",
   "desde": "2025-03-31",
   "hasta": "2026-03-31",
   "piezas": {
    "anualPrevio": 225267000.0,
    "acumuladoPrevio": -14044000.0,
    "acumuladoActual": 40590000.0,
    "anio": 2026,
    "trimestre": 1
   },
   "fuente": {
    "intermedio": "EE.FF. intermedios 2026-T1 (SMV, presentado 30/04/2026)",
    "anual": "EE.FF. anuales 2025 (SMV, presentado 31/03/2026)"
   }
  },
  "LAIVEBC1": {
   "fcf": 50835000.0,
   "monedaXbrl": "PEN",
   "desde": "2025-03-31",
   "hasta": "2026-03-31",
   "piezas": {
    "anualPrevio": 36273000.0,
    "acumuladoPrevio": -6843000.0,
    "acumuladoActual": 7719000.0,
    "anio": 2026,
    "trimestre": 1
   },
   "fuente": {
    "intermedio": "EE.FF. intermedios 2026-T1 (SMV, presentado 30/04/2026)",
    "anual": "EE.FF. anuales 2025 (SMV, presentado 11/03/2026)"
   }
  },
  "CRETEXC1": {
   "fcf": 1848000.0,
   "monedaXbrl": "PEN",
   "desde": "2025-03-31",
   "hasta": "2026-03-31",
   "piezas": {
    "anualPrevio": -5387000.0,
    "acumuladoPrevio": -6261000.0,
    "acumuladoActual": 974000.0,
    "anio": 2026,
    "trimestre": 1
   },
   "fuente": {
    "intermedio": "EE.FF. intermedios 2026-T1 (SMV, presentado 30/04/2026)",
    "anual": "EE.FF. anuales 2025 (SMV, presentado 27/03/2026)"
   }
  },
  "MICHEI1": {
   "fcf": -35621000.0,
   "monedaXbrl": "PEN",
   "desde": "2025-03-31",
   "hasta": "2026-03-31",
   "piezas": {
    "anualPrevio": 5169000.0,
    "acumuladoPrevio": -24096000.0,
    "acumuladoActual": -64886000.0,
    "anio": 2026,
    "trimestre": 1
   },
   "fuente": {
    "intermedio": "EE.FF. intermedios 2026-T1 (SMV, presentado 30/04/2026)",
    "anual": "EE.FF. anuales 2025 (SMV, presentado 22/04/2026)"
   }
  },
  "FILAMEI1": {
   "fcf": 9603000.0,
   "monedaXbrl": "PEN",
   "desde": "2025-03-31",
   "hasta": "2026-03-31",
   "piezas": {
    "anualPrevio": 6594000.0,
    "acumuladoPrevio": -2772000.0,
    "acumuladoActual": 237000.0,
    "anio": 2026,
    "trimestre": 1
   },
   "fuente": {
    "intermedio": "EE.FF. intermedios 2026-T1 (SMV, presentado 30/04/2026)",
    "anual": "EE.FF. anuales 2025 (SMV, presentado 31/03/2026)"
   }
  },
  "CORAREI1": {
   "fcf": 535119000.0,
   "monedaXbrl": "PEN",
   "desde": "2025-03-31",
   "hasta": "2026-03-31",
   "piezas": {
    "anualPrevio": 638461000.0,
    "acumuladoPrevio": 170835000.0,
    "acumuladoActual": 67493000.0,
    "anio": 2026,
    "trimestre": 1
   },
   "fuente": {
    "intermedio": "EE.FF. intermedios 2026-T1 (SMV, presentado 28/04/2026)",
    "anual": "EE.FF. anuales 2025 (SMV, presentado 23/03/2026)"
   }
  },
  "SIDERC1": {
   "fcf": 384226000.0,
   "monedaXbrl": "PEN",
   "desde": "2025-03-31",
   "hasta": "2026-03-31",
   "piezas": {
    "anualPrevio": 291117000.0,
    "acumuladoPrevio": -36576000.0,
    "acumuladoActual": 56533000.0,
    "anio": 2026,
    "trimestre": 1
   },
   "fuente": {
    "intermedio": "EE.FF. intermedios 2026-T1 (SMV, presentado 30/04/2026)",
    "anual": "EE.FF. anuales 2025 (SMV, presentado 27/03/2026)"
   }
  },
  "SHPC1": {
   "fcf": 1023109000.0,
   "monedaXbrl": "PEN",
   "desde": "2025-03-31",
   "hasta": "2026-03-31",
   "piezas": {
    "anualPrevio": 1029743000.0,
    "acumuladoPrevio": 359596000.0,
    "acumuladoActual": 352962000.0,
    "anio": 2026,
    "trimestre": 1
   },
   "fuente": {
    "intermedio": "EE.FF. intermedios 2026-T1 (SMV, presentado 25/04/2026)",
    "anual": "EE.FF. anuales 2025 (SMV, presentado 23/03/2026)"
   }
  },
  "AUSTRAC1": {
   "fcf": 75452000.0,
   "monedaXbrl": "PEN",
   "desde": "2025-03-31",
   "hasta": "2026-03-31",
   "piezas": {
    "anualPrevio": 5912000.0,
    "acumuladoPrevio": -32474000.0,
    "acumuladoActual": 37066000.0,
    "anio": 2026,
    "trimestre": 1
   },
   "fuente": {
    "intermedio": "EE.FF. intermedios 2026-T1 (SMV, presentado 30/04/2026)",
    "anual": "EE.FF. anuales 2025 (SMV, presentado 30/03/2026)"
   }
  },
  "EXALMC1": {
   "fcf": 49585000.0,
   "monedaXbrl": "USD",
   "desde": "2025-03-31",
   "hasta": "2026-03-31",
   "piezas": {
    "anualPrevio": 39150000.0,
    "acumuladoPrevio": 13624000.0,
    "acumuladoActual": 24059000.0,
    "anio": 2026,
    "trimestre": 1
   },
   "fuente": {
    "intermedio": "EE.FF. intermedios 2026-T1 (SMV, presentado 29/04/2026)",
    "anual": "EE.FF. anuales 2025 (SMV, presentado 30/03/2026)"
   }
  },
  "VOLCABC1": {
   "fcf": 197793005.26,
   "monedaXbrl": "USD",
   "desde": "2025-03-31",
   "hasta": "2026-03-31",
   "piezas": {
    "anualPrevio": 208662005.26,
    "acumuladoPrevio": 72430000.0,
    "acumuladoActual": 61561000.0,
    "anio": 2026,
    "trimestre": 1
   },
   "fuente": {
    "intermedio": "EE.FF. intermedios 2026-T1 (SMV, presentado 23/04/2026)",
    "anual": "EE.FF. anuales 2025 (SMV, presentado 26/03/2026)"
   }
  },
  "MINSURI1": {
   "fcf": 395733000.0,
   "monedaXbrl": "USD",
   "desde": "2025-03-31",
   "hasta": "2026-03-31",
   "piezas": {
    "anualPrevio": 380595000.0,
    "acumuladoPrevio": 51533000.0,
    "acumuladoActual": 66671000.0,
    "anio": 2026,
    "trimestre": 1
   },
   "fuente": {
    "intermedio": "EE.FF. intermedios 2026-T1 (SMV, presentado 30/04/2026)",
    "anual": "EE.FF. anuales 2025 (SMV, presentado 25/03/2026)"
   }
  },
  "BROCALC1": {
   "fcf": 102924000.0,
   "monedaXbrl": "USD",
   "desde": "2025-03-31",
   "hasta": "2026-03-31",
   "piezas": {
    "anualPrevio": 92485000.0,
    "acumuladoPrevio": 8616000.0,
    "acumuladoActual": 19055000.0,
    "anio": 2026,
    "trimestre": 1
   },
   "fuente": {
    "intermedio": "EE.FF. intermedios 2026-T1 (SMV, presentado 21/04/2026)",
    "anual": "EE.FF. anuales 2025 (SMV, presentado 23/03/2026)"
   }
  },
  "BACKUSI1": {
   "fcf": 2145132000.0,
   "monedaXbrl": "PEN",
   "desde": "2025-03-31",
   "hasta": "2026-03-31",
   "piezas": {
    "anualPrevio": 2042239000.0,
    "acumuladoPrevio": 7920000.0,
    "acumuladoActual": 110813000.0,
    "anio": 2026,
    "trimestre": 1
   },
   "fuente": {
    "intermedio": "EE.FF. intermedios 2026-T1 (SMV, presentado 30/04/2026)",
    "anual": "EE.FF. anuales 2025 (SMV, presentado 07/04/2026)"
   }
  },
  "SNJUANI1": {
   "fcf": 431836000.0,
   "monedaXbrl": "PEN",
   "desde": "2025-03-31",
   "hasta": "2026-03-31",
   "piezas": {
    "anualPrevio": 417108000.0,
    "acumuladoPrevio": 53312000.0,
    "acumuladoActual": 68040000.0,
    "anio": 2026,
    "trimestre": 1
   },
   "fuente": {
    "intermedio": "EE.FF. intermedios 2026-T1 (SMV, presentado 30/04/2026)",
    "anual": "EE.FF. anuales 2025 (SMV, presentado 07/04/2026)"
   }
  },
  "CASAGRC1": {
   "fcf": 50755000.0,
   "monedaXbrl": "PEN",
   "desde": "2025-03-31",
   "hasta": "2026-03-31",
   "piezas": {
    "anualPrevio": 20597000.0,
    "acumuladoPrevio": -17674000.0,
    "acumuladoActual": 12484000.0,
    "anio": 2026,
    "trimestre": 1
   },
   "fuente": {
    "intermedio": "EE.FF. intermedios 2026-T1 (SMV, presentado 30/04/2026)",
    "anual": "EE.FF. anuales 2025 (SMV, presentado 25/03/2026)"
   }
  },
  "LUSURC1": {
   "fcf": 349471000.0,
   "monedaXbrl": "PEN",
   "desde": "2025-03-31",
   "hasta": "2026-03-31",
   "piezas": {
    "anualPrevio": 371444000.0,
    "acumuladoPrevio": 121217000.0,
    "acumuladoActual": 99244000.0,
    "anio": 2026,
    "trimestre": 1
   },
   "fuente": {
    "intermedio": "EE.FF. intermedios 2026-T1 (SMV, presentado 30/04/2026)",
    "anual": "EE.FF. anuales 2025 (SMV, presentado 26/03/2026)"
   }
  },
  "ENGIEC1": {
   "fcf": 132413000.0,
   "monedaXbrl": "USD",
   "desde": "2025-03-31",
   "hasta": "2026-03-31",
   "piezas": {
    "anualPrevio": 131436000.0,
    "acumuladoPrevio": 44693000.0,
    "acumuladoActual": 45670000.0,
    "anio": 2026,
    "trimestre": 1
   },
   "fuente": {
    "intermedio": "EE.FF. intermedios 2026-T1 (SMV, presentado 29/04/2026)",
    "anual": "EE.FF. anuales 2025 (SMV, presentado 26/03/2026)"
   }
  },
  "ORYGENC1": {
   "fcf": 744273000.0,
   "monedaXbrl": "PEN",
   "desde": "2025-03-31",
   "hasta": "2026-03-31",
   "piezas": {
    "anualPrevio": 891535000.0,
    "acumuladoPrevio": 181184000.0,
    "acumuladoActual": 33922000.0,
    "anio": 2026,
    "trimestre": 1
   },
   "fuente": {
    "intermedio": "EE.FF. intermedios 2026-T1 (SMV, presentado 30/04/2026)",
    "anual": "EE.FF. anuales 2025 (SMV, presentado 30/03/2026)"
   }
  },
  "CPACASC1": {
   "fcf": 175791000.0,
   "monedaXbrl": "PEN",
   "desde": "2025-03-31",
   "hasta": "2026-03-31",
   "piezas": {
    "anualPrevio": 207281000.0,
    "acumuladoPrevio": 31613000.0,
    "acumuladoActual": 123000.0,
    "anio": 2026,
    "trimestre": 1
   },
   "fuente": {
    "intermedio": "EE.FF. intermedios 2026-T1 (SMV, presentado 24/04/2026)",
    "anual": "EE.FF. anuales 2025 (SMV, presentado 24/03/2026)"
   }
  },
  "UNACEMC1": {
   "fcf": 349827000.0,
   "monedaXbrl": "PEN",
   "desde": "2025-03-31",
   "hasta": "2026-03-31",
   "piezas": {
    "anualPrevio": 359159000.0,
    "acumuladoPrevio": 143111000.0,
    "acumuladoActual": 133779000.0,
    "anio": 2026,
    "trimestre": 1
   },
   "fuente": {
    "intermedio": "EE.FF. intermedios 2026-T1 (SMV, presentado 29/04/2026)",
    "anual": "EE.FF. anuales 2025 (SMV, presentado 31/03/2026)"
   }
  },
  "FERREYC1": {
   "fcf": 447091000.0,
   "monedaXbrl": "PEN",
   "desde": "2025-03-31",
   "hasta": "2026-03-31",
   "piezas": {
    "anualPrevio": 372425000.0,
    "acumuladoPrevio": 23587000.0,
    "acumuladoActual": 98253000.0,
    "anio": 2026,
    "trimestre": 1
   },
   "fuente": {
    "intermedio": "EE.FF. intermedios 2026-T1 (SMV, presentado 29/04/2026)",
    "anual": "EE.FF. anuales 2025 (SMV, presentado 25/03/2026)"
   }
  },
  "INRETC1": {
   "fcf": 459757000.0,
   "monedaXbrl": "PEN",
   "desde": "2025-03-31",
   "hasta": "2026-03-31",
   "piezas": {
    "anualPrevio": 395891000.0,
    "acumuladoPrevio": 109570000.0,
    "acumuladoActual": 173436000.0,
    "anio": 2026,
    "trimestre": 1
   },
   "fuente": {
    "intermedio": "EE.FF. intermedios 2026-T1 (SMV, presentado 30/04/2026)",
    "anual": "EE.FF. anuales 2025 (SMV, presentado 31/03/2026)"
   }
  },
  "IFS": {
   "fcf": -55369000.0,
   "monedaXbrl": "PEN",
   "desde": "2025-03-31",
   "hasta": "2026-03-31",
   "piezas": {
    "anualPrevio": -56977000.0,
    "acumuladoPrevio": -5921000.0,
    "acumuladoActual": -4313000.0,
    "anio": 2026,
    "trimestre": 1
   },
   "fuente": {
    "intermedio": "EE.FF. intermedios 2026-T1 (SMV, presentado 11/05/2026)",
    "anual": "EE.FF. anuales 2025 (SMV, presentado 31/03/2026)"
   }
  },
  "AENZAC1": {
   "fcf": -251945000.0,
   "monedaXbrl": "PEN",
   "desde": "2025-03-31",
   "hasta": "2026-03-31",
   "piezas": {
    "anualPrevio": -273663000.0,
    "acumuladoPrevio": -30338000.0,
    "acumuladoActual": -8620000.0,
    "anio": 2026,
    "trimestre": 1
   },
   "fuente": {
    "intermedio": "EE.FF. intermedios 2026-T1 (SMV, presentado 30/04/2026)",
    "anual": "EE.FF. anuales 2025 (SMV, presentado 25/03/2026)"
   }
  },
  "PODERC1": {
   "fcf": 1139265000.0,
   "monedaXbrl": "PEN",
   "desde": "2025-03-31",
   "hasta": "2026-03-31",
   "piezas": {
    "anualPrevio": 1119860000.0,
    "acumuladoPrevio": 232571000.0,
    "acumuladoActual": 251976000.0,
    "anio": 2026,
    "trimestre": 1
   },
   "fuente": {
    "intermedio": "EE.FF. intermedios 2026-T1 (SMV, presentado 29/04/2026)",
    "anual": "EE.FF. anuales 2025 (SMV, presentado 24/03/2026)"
   }
  },
  "SPCCPI1": {
   "fcf": 2098110000.0,
   "monedaXbrl": "USD",
   "desde": "2025-03-31",
   "hasta": "2026-03-31",
   "piezas": {
    "anualPrevio": 1838206000.0,
    "acumuladoPrevio": 324721000.0,
    "acumuladoActual": 584625000.0,
    "anio": 2026,
    "trimestre": 1
   },
   "fuente": {
    "intermedio": "EE.FF. intermedios 2026-T1 (SMV, presentado 30/04/2026)",
    "anual": "EE.FF. anuales 2025 (SMV, presentado 26/03/2026)"
   }
  },
  "MINCORI1": {
   "fcf": 104482000.0,
   "monedaXbrl": "USD",
   "desde": "2025-03-31",
   "hasta": "2026-03-31",
   "piezas": {
    "anualPrevio": 59057000.0,
    "acumuladoPrevio": 15050000.0,
    "acumuladoActual": 60475000.0,
    "anio": 2026,
    "trimestre": 1
   },
   "fuente": {
    "intermedio": "EE.FF. intermedios 2026-T1 (SMV, presentado 28/04/2026)",
    "anual": "EE.FF. anuales 2025 (SMV, presentado 31/03/2026)"
   }
  },
  "ATACOBC1": {
   "fcf": 30894000.0,
   "monedaXbrl": "USD",
   "desde": "2025-03-31",
   "hasta": "2026-03-31",
   "piezas": {
    "anualPrevio": 18443000.0,
    "acumuladoPrevio": -8250000.0,
    "acumuladoActual": 4201000.0,
    "anio": 2026,
    "trimestre": 1
   },
   "fuente": {
    "intermedio": "EE.FF. intermedios 2026-T1 (SMV, presentado 06/05/2026)",
    "anual": "EE.FF. anuales 2025 (SMV, presentado 31/03/2026)"
   }
  },
  "CARTAVC1": {
   "fcf": 80449000.0,
   "monedaXbrl": "PEN",
   "desde": "2025-03-31",
   "hasta": "2026-03-31",
   "piezas": {
    "anualPrevio": 65685000.0,
    "acumuladoPrevio": -10533000.0,
    "acumuladoActual": 4231000.0,
    "anio": 2026,
    "trimestre": 1
   },
   "fuente": {
    "intermedio": "EE.FF. intermedios 2026-T1 (SMV, presentado 30/04/2026)",
    "anual": "EE.FF. anuales 2025 (SMV, presentado 26/03/2026)"
   }
  },
  "POMALCC1": {
   "fcf": -1592000.0,
   "monedaXbrl": "PEN",
   "desde": "2025-03-31",
   "hasta": "2026-03-31",
   "piezas": {
    "anualPrevio": 4171000.0,
    "acumuladoPrevio": 837000.0,
    "acumuladoActual": -4926000.0,
    "anio": 2026,
    "trimestre": 1
   },
   "fuente": {
    "intermedio": "EE.FF. intermedios 2026-T1 (SMV, presentado 29/04/2026)",
    "anual": "EE.FF. anuales 2025 (SMV, presentado 31/03/2026)"
   }
  },
  "HIDRA2C1": {
   "fcf": 64545000.0,
   "monedaXbrl": "PEN",
   "desde": "2025-03-31",
   "hasta": "2026-03-31",
   "piezas": {
    "anualPrevio": 37946000.0,
    "acumuladoPrevio": -12263000.0,
    "acumuladoActual": 14336000.0,
    "anio": 2026,
    "trimestre": 1
   },
   "fuente": {
    "intermedio": "EE.FF. intermedios 2026-T1 (SMV, presentado 30/04/2026)",
    "anual": "EE.FF. anuales 2025 (SMV, presentado 01/04/2026)"
   }
  },
  "PLUZENC1": {
   "fcf": 643155000.0,
   "monedaXbrl": "PEN",
   "desde": "2025-03-31",
   "hasta": "2026-03-31",
   "piezas": {
    "anualPrevio": 202069000.0,
    "acumuladoPrevio": -155698000.0,
    "acumuladoActual": 285388000.0,
    "anio": 2026,
    "trimestre": 1
   },
   "fuente": {
    "intermedio": "EE.FF. intermedios 2026-T1 (SMV, presentado 29/04/2026)",
    "anual": "EE.FF. anuales 2025 (SMV, presentado 26/03/2026)"
   }
  },
  "GRHOLDC1": {
   "fcf": -51667000.0,
   "monedaXbrl": "PEN",
   "desde": "2025-03-31",
   "hasta": "2026-03-31",
   "piezas": {
    "anualPrevio": -17687000.0,
    "acumuladoPrevio": 32815000.0,
    "acumuladoActual": -1165000.0,
    "anio": 2026,
    "trimestre": 1
   },
   "fuente": {
    "intermedio": "EE.FF. intermedios 2026-T1 (SMV, presentado 29/04/2026)",
    "anual": "EE.FF. anuales 2025 (SMV, presentado 31/03/2026)"
   }
  },
  "BAMC1": {
   "fcf": -16258000.0,
   "monedaXbrl": "USD",
   "desde": "2025-03-31",
   "hasta": "2026-03-31",
   "piezas": {
    "anualPrevio": -15001000.0,
    "acumuladoPrevio": -2874000.0,
    "acumuladoActual": -4131000.0,
    "anio": 2026,
    "trimestre": 1
   },
   "fuente": {
    "intermedio": "EE.FF. intermedios 2026-T1 (SMV, presentado 28/04/2026)",
    "anual": "EE.FF. anuales 2025 (SMV, presentado 31/03/2026)"
   }
  },
  "ELCOMEI1": {
   "fcf": 24455000.0,
   "monedaXbrl": "PEN",
   "desde": "2025-03-31",
   "hasta": "2026-03-31",
   "piezas": {
    "anualPrevio": 23997000.0,
    "acumuladoPrevio": 1855000.0,
    "acumuladoActual": 2313000.0,
    "anio": 2026,
    "trimestre": 1
   },
   "fuente": {
    "intermedio": "EE.FF. intermedios 2026-T1 (SMV, presentado 30/04/2026)",
    "anual": "EE.FF. anuales 2025 (SMV, presentado 19/03/2026)"
   }
  },
  "TRADIC1": {
   "fcf": -86214000.0,
   "monedaXbrl": "PEN",
   "desde": "2025-03-31",
   "hasta": "2026-03-31",
   "piezas": {
    "anualPrevio": -21203000.0,
    "acumuladoPrevio": 31604000.0,
    "acumuladoActual": -33407000.0,
    "anio": 2026,
    "trimestre": 1
   },
   "fuente": {
    "intermedio": "EE.FF. intermedios 2026-T1 (SMV, presentado 30/04/2026)",
    "anual": "EE.FF. anuales 2025 (SMV, presentado 07/04/2026)"
   }
  },
  "SEALDC1": {
   "fcf": 79640000.0,
   "monedaXbrl": "PEN",
   "desde": "2025-03-31",
   "hasta": "2026-03-31",
   "piezas": {
    "anualPrevio": 63171000.0,
    "acumuladoPrevio": 7687000.0,
    "acumuladoActual": 24156000.0,
    "anio": 2026,
    "trimestre": 1
   },
   "fuente": {
    "intermedio": "EE.FF. intermedios 2026-T1 (SMV, presentado 27/04/2026)",
    "anual": "EE.FF. anuales 2025 (SMV, presentado 31/03/2026)"
   }
  },
  "PERENBC1": {
   "fcf": 2631000.0,
   "monedaXbrl": "PEN",
   "desde": "2025-03-31",
   "hasta": "2026-03-31",
   "piezas": {
    "anualPrevio": 31814000.0,
    "acumuladoPrevio": 30854000.0,
    "acumuladoActual": 1671000.0,
    "anio": 2026,
    "trimestre": 1
   },
   "fuente": {
    "intermedio": "EE.FF. intermedios 2026-T1 (SMV, presentado 30/04/2026)",
    "anual": "EE.FF. anuales 2025 (SMV, presentado 27/03/2026)"
   }
  },
  "EGEPIBC1": {
   "fcf": 69910000.0,
   "monedaXbrl": "PEN",
   "desde": "2025-03-31",
   "hasta": "2026-03-31",
   "piezas": {
    "anualPrevio": 83387000.0,
    "acumuladoPrevio": 21513000.0,
    "acumuladoActual": 8036000.0,
    "anio": 2026,
    "trimestre": 1
   },
   "fuente": {
    "intermedio": "EE.FF. intermedios 2026-T1 (SMV, presentado 30/04/2026)",
    "anual": "EE.FF. anuales 2025 (SMV, presentado 30/03/2026)"
   }
  },
  "LUISAI1": {
   "fcf": 153455000.0,
   "monedaXbrl": "PEN",
   "desde": "2025-03-31",
   "hasta": "2026-03-31",
   "piezas": {
    "anualPrevio": 115326000.0,
    "acumuladoPrevio": 17104000.0,
    "acumuladoActual": 55233000.0,
    "anio": 2026,
    "trimestre": 1
   },
   "fuente": {
    "intermedio": "EE.FF. intermedios 2026-T1 (SMV, presentado 29/04/2026)",
    "anual": "EE.FF. anuales 2025 (SMV, presentado 30/03/2026)"
   }
  },
  "MOROCOI1": {
   "fcf": -48281000.0,
   "monedaXbrl": "PEN",
   "desde": "2025-03-31",
   "hasta": "2026-03-31",
   "piezas": {
    "anualPrevio": -37920000.0,
    "acumuladoPrevio": -16599000.0,
    "acumuladoActual": -26960000.0,
    "anio": 2026,
    "trimestre": 1
   },
   "fuente": {
    "intermedio": "EE.FF. intermedios 2026-T1 (SMV, presentado 30/04/2026)",
    "anual": "EE.FF. anuales 2025 (SMV, presentado 31/03/2026)"
   }
  },
  "SNJACIC1": {
   "fcf": 39456000.0,
   "monedaXbrl": "PEN",
   "desde": "2025-03-31",
   "hasta": "2026-03-31",
   "piezas": {
    "anualPrevio": 22544000.0,
    "acumuladoPrevio": 7157000.0,
    "acumuladoActual": 24069000.0,
    "anio": 2026,
    "trimestre": 1
   },
   "fuente": {
    "intermedio": "EE.FF. intermedios 2026-T1 (SMV, presentado 30/04/2026)",
    "anual": "EE.FF. anuales 2025 (SMV, presentado 26/03/2026)"
   }
  },
  "LAREDOC1": {
   "fcf": -46000.0,
   "monedaXbrl": "PEN",
   "desde": "2025-03-31",
   "hasta": "2026-03-31",
   "piezas": {
    "anualPrevio": -1211000.0,
    "acumuladoPrevio": -15673000.0,
    "acumuladoActual": -14508000.0,
    "anio": 2026,
    "trimestre": 1
   },
   "fuente": {
    "intermedio": "EE.FF. intermedios 2026-T1 (SMV, presentado 30/04/2026)",
    "anual": "EE.FF. anuales 2025 (SMV, presentado 26/03/2026)"
   }
  },
  "ETNAI1": {
   "fcf": 1751000.0,
   "monedaXbrl": "PEN",
   "desde": "2025-03-31",
   "hasta": "2026-03-31",
   "piezas": {
    "anualPrevio": -1979000.0,
    "acumuladoPrevio": -10375000.0,
    "acumuladoActual": -6645000.0,
    "anio": 2026,
    "trimestre": 1
   },
   "fuente": {
    "intermedio": "EE.FF. intermedios 2026-T1 (SMV, presentado 21/04/2026)",
    "anual": "EE.FF. anuales 2025 (SMV, presentado 08/04/2026)"
   }
  },
  "INTPEBC1": {
   "fcf": 132411000.0,
   "monedaXbrl": "PEN",
   "desde": "2025-03-31",
   "hasta": "2026-03-31",
   "piezas": {
    "anualPrevio": -361728000.0,
    "acumuladoPrevio": -515370000.0,
    "acumuladoActual": -21231000.0,
    "anio": 2026,
    "trimestre": 1
   },
   "fuente": {
    "intermedio": "EE.FF. intermedios 2026-T1 (SMV, presentado 30/04/2026)",
    "anual": "EE.FF. anuales 2025 (SMV, presentado 31/03/2026)"
   }
  },
  "INVCENC1": {
   "fcf": 79349000.0,
   "monedaXbrl": "PEN",
   "desde": "2025-03-31",
   "hasta": "2026-03-31",
   "piezas": {
    "anualPrevio": 89117000.0,
    "acumuladoPrevio": 22717000.0,
    "acumuladoActual": 12949000.0,
    "anio": 2026,
    "trimestre": 1
   },
   "fuente": {
    "intermedio": "EE.FF. intermedios 2026-T1 (SMV, presentado 30/04/2026)",
    "anual": "EE.FF. anuales 2025 (SMV, presentado 24/03/2026)"
   }
  },
  "AIHC1": {
   "fcf": -569000.0,
   "monedaXbrl": "PEN",
   "desde": "2025-03-31",
   "hasta": "2026-03-31",
   "piezas": {
    "anualPrevio": -10333000.0,
    "acumuladoPrevio": -1514000.0,
    "acumuladoActual": 8250000.0,
    "anio": 2026,
    "trimestre": 1
   },
   "fuente": {
    "intermedio": "EE.FF. intermedios 2026-T1 (SMV, presentado 30/04/2026)",
    "anual": "EE.FF. anuales 2025 (SMV, presentado 31/03/2026)"
   }
  },
  "ENPACII1": {
   "fcf": -737000.0,
   "monedaXbrl": "USD",
   "desde": "2025-03-31",
   "hasta": "2026-03-31",
   "piezas": {
    "anualPrevio": -726000.0,
    "acumuladoPrevio": 63000.0,
    "acumuladoActual": 52000.0,
    "anio": 2026,
    "trimestre": 1
   },
   "fuente": {
    "intermedio": "EE.FF. intermedios 2026-T1 (SMV, presentado 30/04/2026)",
    "anual": "EE.FF. anuales 2025 (SMV, presentado 26/03/2026)"
   }
  },
  "CONCESI1": {
   "fcf": -5328000.0,
   "monedaXbrl": "PEN",
   "desde": "2025-03-31",
   "hasta": "2026-03-31",
   "piezas": {
    "anualPrevio": -3837000.0,
    "acumuladoPrevio": -356000.0,
    "acumuladoActual": -1847000.0,
    "anio": 2026,
    "trimestre": 1
   },
   "fuente": {
    "intermedio": "EE.FF. intermedios 2026-T1 (SMV, presentado 30/04/2026)",
    "anual": "EE.FF. anuales 2025 (SMV, presentado 31/03/2026)"
   }
  },
  "SAGAC1": {
   "fcf": 531245000.0,
   "monedaXbrl": "PEN",
   "desde": "2025-03-31",
   "hasta": "2026-03-31",
   "piezas": {
    "anualPrevio": 467096000.0,
    "acumuladoPrevio": -151044000.0,
    "acumuladoActual": -86895000.0,
    "anio": 2026,
    "trimestre": 1
   },
   "fuente": {
    "intermedio": "EE.FF. intermedios 2026-T1 (SMV, presentado 30/04/2026)",
    "anual": "EE.FF. anuales 2025 (SMV, presentado 13/03/2026)"
   }
  },
  "COCESUI1": {
   "fcf": 13977000.0,
   "monedaXbrl": "PEN",
   "desde": "2025-03-31",
   "hasta": "2026-03-31",
   "piezas": {
    "anualPrevio": 799000.0,
    "acumuladoPrevio": -10314000.0,
    "acumuladoActual": 2864000.0,
    "anio": 2026,
    "trimestre": 1
   },
   "fuente": {
    "intermedio": "EE.FF. intermedios 2026-T1 (SMV, presentado 23/04/2026)",
    "anual": "EE.FF. anuales 2025 (SMV, presentado 26/03/2026)"
   }
  },
  "FOSSALC1": {
   "fcf": -1437000.0,
   "monedaXbrl": "PEN",
   "desde": "2025-03-31",
   "hasta": "2026-03-31",
   "piezas": {
    "anualPrevio": -944000.0,
    "acumuladoPrevio": -36000.0,
    "acumuladoActual": -529000.0,
    "anio": 2026,
    "trimestre": 1
   },
   "fuente": {
    "intermedio": "EE.FF. intermedios 2026-T1 (SMV, presentado 30/04/2026)",
    "anual": "EE.FF. anuales 2025 (SMV, presentado 24/03/2026)"
   }
  },
  "HERMESC1": {
   "fcf": 85689000.0,
   "monedaXbrl": "PEN",
   "desde": "2025-03-31",
   "hasta": "2026-03-31",
   "piezas": {
    "anualPrevio": 113858000.0,
    "acumuladoPrevio": 33616000.0,
    "acumuladoActual": 5447000.0,
    "anio": 2026,
    "trimestre": 1
   },
   "fuente": {
    "intermedio": "EE.FF. intermedios 2026-T1 (SMV, presentado 30/04/2026)",
    "anual": "EE.FF. anuales 2025 (SMV, presentado 26/03/2026)"
   }
  },
  "CRECAPC1": {
   "fcf": 40454000.0,
   "monedaXbrl": "PEN",
   "desde": "2025-03-31",
   "hasta": "2026-03-31",
   "piezas": {
    "anualPrevio": 40537000.0,
    "acumuladoPrevio": -166000.0,
    "acumuladoActual": -249000.0,
    "anio": 2026,
    "trimestre": 1
   },
   "fuente": {
    "intermedio": "EE.FF. intermedios 2026-T1 (SMV, presentado 30/04/2026)",
    "anual": "EE.FF. anuales 2025 (SMV, presentado 31/03/2026)"
   }
  },
  "INDECOI1": {
   "fcf": 346162000.0,
   "monedaXbrl": "USD",
   "desde": "2025-03-31",
   "hasta": "2026-03-31",
   "piezas": {
    "anualPrevio": 343466000.0,
    "acumuladoPrevio": 89087000.0,
    "acumuladoActual": 91783000.0,
    "anio": 2026,
    "trimestre": 1
   },
   "fuente": {
    "intermedio": "EE.FF. intermedios 2026-T1 (SMV, presentado 29/04/2026)",
    "anual": "EE.FF. anuales 2025 (SMV, presentado 24/03/2026)"
   }
  },
  "GBVLAC1": {
   "fcf": 3849000.0,
   "monedaXbrl": "PEN",
   "desde": "2025-03-31",
   "hasta": "2026-03-31",
   "piezas": {
    "anualPrevio": 7200000.0,
    "acumuladoPrevio": 4772000.0,
    "acumuladoActual": 1421000.0,
    "anio": 2026,
    "trimestre": 1
   },
   "fuente": {
    "intermedio": "EE.FF. intermedios 2026-T1 (SMV, presentado 23/04/2026)",
    "anual": "EE.FF. anuales 2025 (SMV, presentado 23/03/2026)"
   }
  },
  "ANDEXBC1": {
   "fcf": -1549000.0,
   "monedaXbrl": "PEN",
   "desde": "2025-03-31",
   "hasta": "2026-03-31",
   "piezas": {
    "anualPrevio": -1410000.0,
    "acumuladoPrevio": -52000.0,
    "acumuladoActual": -191000.0,
    "anio": 2026,
    "trimestre": 1
   },
   "fuente": {
    "intermedio": "EE.FF. intermedios 2026-T1 (SMV, presentado 30/04/2026)",
    "anual": "EE.FF. anuales 2025 (SMV, presentado 31/03/2026)"
   }
  },
  "QUIMPAI1": {
   "fcf": 71292000.0,
   "monedaXbrl": "USD",
   "desde": "2025-03-31",
   "hasta": "2026-03-31",
   "piezas": {
    "anualPrevio": 44709000.0,
    "acumuladoPrevio": -3649000.0,
    "acumuladoActual": 22934000.0,
    "anio": 2026,
    "trimestre": 1
   },
   "fuente": {
    "intermedio": "EE.FF. intermedios 2026-T1 (SMV, presentado 30/04/2026)",
    "anual": "EE.FF. anuales 2025 (SMV, presentado 25/03/2026)"
   }
  },
  "HIDROSI1": {
   "fcf": 13138000.0,
   "monedaXbrl": "PEN",
   "desde": "2025-03-31",
   "hasta": "2026-03-31",
   "piezas": {
    "anualPrevio": 6738000.0,
    "acumuladoPrevio": -4673000.0,
    "acumuladoActual": 1727000.0,
    "anio": 2026,
    "trimestre": 1
   },
   "fuente": {
    "intermedio": "EE.FF. intermedios 2026-T1 (SMV, presentado 30/04/2026)",
    "anual": "EE.FF. anuales 2025 (SMV, presentado 27/03/2026)"
   }
  },
  "ETERNII1": {
   "fcf": 16555000.0,
   "monedaXbrl": "PEN",
   "desde": "2025-03-31",
   "hasta": "2026-03-31",
   "piezas": {
    "anualPrevio": 3353000.0,
    "acumuladoPrevio": -175000.0,
    "acumuladoActual": 13027000.0,
    "anio": 2026,
    "trimestre": 1
   },
   "fuente": {
    "intermedio": "EE.FF. intermedios 2026-T1 (SMV, presentado 30/04/2026)",
    "anual": "EE.FF. anuales 2025 (SMV, presentado 31/03/2026)"
   }
  },
  "PERUBAI1": {
   "fcf": 12535000.0,
   "monedaXbrl": "USD",
   "desde": "2025-03-31",
   "hasta": "2026-03-31",
   "piezas": {
    "anualPrevio": 11482000.0,
    "acumuladoPrevio": 2799000.0,
    "acumuladoActual": 3852000.0,
    "anio": 2026,
    "trimestre": 1
   },
   "fuente": {
    "intermedio": "EE.FF. intermedios 2026-T1 (SMV, presentado 29/04/2026)",
    "anual": "EE.FF. anuales 2025 (SMV, presentado 31/03/2026)"
   }
  },
  "INVFALC1": {
   "fcf": 35701000.0,
   "monedaXbrl": "PEN",
   "desde": "2025-03-31",
   "hasta": "2026-03-31",
   "piezas": {
    "anualPrevio": -32027000.0,
    "acumuladoPrevio": -473322000.0,
    "acumuladoActual": -405594000.0,
    "anio": 2026,
    "trimestre": 1
   },
   "fuente": {
    "intermedio": "EE.FF. intermedios 2026-T1 (SMV, presentado 30/04/2026)",
    "anual": "EE.FF. anuales 2025 (SMV, presentado 17/03/2026)"
   }
  },
  "FUTURAI1": {
   "fcf": 7145000.0,
   "monedaXbrl": "PEN",
   "desde": "2025-03-31",
   "hasta": "2026-03-31",
   "piezas": {
    "anualPrevio": 8719000.0,
    "acumuladoPrevio": 2955000.0,
    "acumuladoActual": 1381000.0,
    "anio": 2026,
    "trimestre": 1
   },
   "fuente": {
    "intermedio": "EE.FF. intermedios 2026-T1 (SMV, presentado 30/04/2026)",
    "anual": "EE.FF. anuales 2025 (SMV, presentado 27/03/2026)"
   }
  },
  "IIDEI1": {
   "fcf": 7005000.0,
   "monedaXbrl": "PEN",
   "desde": "2025-03-31",
   "hasta": "2026-03-31",
   "piezas": {
    "anualPrevio": 6507000.0,
    "acumuladoPrevio": -213000.0,
    "acumuladoActual": 285000.0,
    "anio": 2026,
    "trimestre": 1
   },
   "fuente": {
    "intermedio": "EE.FF. intermedios 2026-T1 (SMV, presentado 30/04/2026)",
    "anual": "EE.FF. anuales 2025 (SMV, presentado 07/04/2026)"
   }
  },
  "ELECPBC1": {
   "fcf": 466823000.0,
   "monedaXbrl": "PEN",
   "desde": "2025-03-31",
   "hasta": "2026-03-31",
   "piezas": {
    "anualPrevio": 552836000.0,
    "acumuladoPrevio": 242678000.0,
    "acumuladoActual": 156665000.0,
    "anio": 2026,
    "trimestre": 1
   },
   "fuente": {
    "intermedio": "EE.FF. intermedios 2026-T1 (SMV, presentado 29/04/2026)",
    "anual": "EE.FF. anuales 2025 (SMV, presentado 27/03/2026)"
   }
  },
  "EDUNASC1": {
   "fcf": 27910000.0,
   "monedaXbrl": "PEN",
   "desde": "2025-03-31",
   "hasta": "2026-03-31",
   "piezas": {
    "anualPrevio": 44655000.0,
    "acumuladoPrevio": 25021000.0,
    "acumuladoActual": 8276000.0,
    "anio": 2026,
    "trimestre": 1
   },
   "fuente": {
    "intermedio": "EE.FF. intermedios 2026-T1 (SMV, presentado 30/04/2026)",
    "anual": "EE.FF. anuales 2025 (SMV, presentado 23/03/2026)"
   }
  },
  "SANGABC1": {
   "fcf": 80750000.0,
   "monedaXbrl": "PEN",
   "desde": "2025-03-31",
   "hasta": "2026-03-31",
   "piezas": {
    "anualPrevio": 71513000.0,
    "acumuladoPrevio": 5472000.0,
    "acumuladoActual": 14709000.0,
    "anio": 2026,
    "trimestre": 1
   },
   "fuente": {
    "intermedio": "EE.FF. intermedios 2026-T1 (SMV, presentado 24/04/2026)",
    "anual": "EE.FF. anuales 2025 (SMV, presentado 30/03/2026)"
   }
  },
  "PORTAC1": {
   "fcf": 273632000.0,
   "monedaXbrl": "PEN",
   "desde": "2025-03-31",
   "hasta": "2026-03-31",
   "piezas": {
    "anualPrevio": 241782000.0,
    "acumuladoPrevio": -7389000.0,
    "acumuladoActual": 24461000.0,
    "anio": 2026,
    "trimestre": 1
   },
   "fuente": {
    "intermedio": "EE.FF. intermedios 2026-T1 (SMV, presentado 30/04/2026)",
    "anual": "EE.FF. anuales 2025 (SMV, presentado 25/03/2026)"
   }
  },
  "SEDAPBC1": {
   "fcf": 744667000.0,
   "monedaXbrl": "PEN",
   "desde": "2025-03-31",
   "hasta": "2026-03-31",
   "piezas": {
    "anualPrevio": 617309000.0,
    "acumuladoPrevio": 95114000.0,
    "acumuladoActual": 222472000.0,
    "anio": 2026,
    "trimestre": 1
   },
   "fuente": {
    "intermedio": "EE.FF. intermedios 2026-T1 (SMV, presentado 30/04/2026)",
    "anual": "EE.FF. anuales 2025 (SMV, presentado 01/07/2026)"
   }
  },
  "ELESUDC1": {
   "fcf": -341000.0,
   "monedaXbrl": "PEN",
   "desde": "2025-03-31",
   "hasta": "2026-03-31",
   "piezas": {
    "anualPrevio": 11352000.0,
    "acumuladoPrevio": 12952000.0,
    "acumuladoActual": 1259000.0,
    "anio": 2026,
    "trimestre": 1
   },
   "fuente": {
    "intermedio": "EE.FF. intermedios 2026-T1 (SMV, presentado 30/04/2026)",
    "anual": "EE.FF. anuales 2025 (SMV, presentado 31/03/2026)"
   }
  },
  "ESUREBC1": {
   "fcf": 58296000.0,
   "monedaXbrl": "PEN",
   "desde": "2025-03-31",
   "hasta": "2026-03-31",
   "piezas": {
    "anualPrevio": 61696000.0,
    "acumuladoPrevio": 30434000.0,
    "acumuladoActual": 27034000.0,
    "anio": 2026,
    "trimestre": 1
   },
   "fuente": {
    "intermedio": "EE.FF. intermedios 2026-T1 (SMV, presentado 29/04/2026)",
    "anual": "EE.FF. anuales 2025 (SMV, presentado 27/04/2026)"
   }
  },
  "RVIA5BC1": {
   "fcf": 126542000.0,
   "monedaXbrl": "PEN",
   "desde": "2025-03-31",
   "hasta": "2026-03-31",
   "piezas": {
    "anualPrevio": 125675000.0,
    "acumuladoPrevio": 25754000.0,
    "acumuladoActual": 26621000.0,
    "anio": 2026,
    "trimestre": 1
   },
   "fuente": {
    "intermedio": "EE.FF. intermedios 2026-T1 (SMV, presentado 30/04/2026)",
    "anual": "EE.FF. anuales 2025 (SMV, presentado 26/03/2026)"
   }
  },
  "INCRAIC1": {
   "fcf": 10095000.0,
   "monedaXbrl": "PEN",
   "desde": "2025-03-31",
   "hasta": "2026-03-31",
   "piezas": {
    "anualPrevio": 13324000.0,
    "acumuladoPrevio": 3329000.0,
    "acumuladoActual": 100000.0,
    "anio": 2026,
    "trimestre": 1
   },
   "fuente": {
    "intermedio": "EE.FF. intermedios 2026-T1 (SMV, presentado 29/04/2026)",
    "anual": "EE.FF. anuales 2025 (SMV, presentado 26/03/2026)"
   }
  },
  "IEQSAI1": {
   "fcf": 8399000.0,
   "monedaXbrl": "USD",
   "desde": "2025-03-31",
   "hasta": "2026-03-31",
   "piezas": {
    "anualPrevio": 5767000.0,
    "acumuladoPrevio": -3409000.0,
    "acumuladoActual": -777000.0,
    "anio": 2026,
    "trimestre": 1
   },
   "fuente": {
    "intermedio": "EE.FF. intermedios 2026-T1 (SMV, presentado 29/04/2026)",
    "anual": "EE.FF. anuales 2025 (SMV, presentado 27/03/2026)"
   }
  },
  "PARAMOC1": {
   "fcf": 31473000.0,
   "monedaXbrl": "PEN",
   "desde": "2025-03-31",
   "hasta": "2026-03-31",
   "piezas": {
    "anualPrevio": 16392000.0,
    "acumuladoPrevio": -21387000.0,
    "acumuladoActual": -6306000.0,
    "anio": 2026,
    "trimestre": 1
   },
   "fuente": {
    "intermedio": "EE.FF. intermedios 2026-T1 (SMV, presentado 30/04/2026)",
    "anual": "EE.FF. anuales 2025 (SMV, presentado 31/03/2026)"
   }
  }
 }
}